private/__init__.py
private/loader.py
private/module_template.txt
private/packages.py
private/processor.py
private/source_tags.py
private-0.3.0.dist-info/LICENSE.txt
private-0.3.0.dist-info/METADATA
private-0.3.0.dist-info/WHEEL
private-0.3.0.dist-info/entry_points.txt
private-0.3.0.dist-info/top_level.txt
private-0.3.0.dist-info/RECORD
