Metadata-Version: 2.1
Name: private
Version: 0.3.0
Summary: Python modules and distribution encryption tool
Home-page: https://gitlab.com/OmerSarig/private
Author: Omer Sarig
Author-email: omer@sarig.co.il
License: UNKNOWN
Keywords: encrypt package wheel obfuscate
Platform: UNKNOWN
Classifier: Development Status :: 2 - Pre-Alpha
Classifier: Environment :: Console
Classifier: Intended Audience :: Developers
Classifier: License :: Freeware
Classifier: Operating System :: POSIX
Classifier: Programming Language :: Python :: 2 :: Only
Classifier: Topic :: Security :: Cryptography
Classifier: Topic :: Software Development :: Build Tools
Requires-Python: >=2.7
Requires-Dist: pyaes
Requires-Dist: click
Requires-Dist: wheelmerge
Requires-Dist: pip
